litepolis_math/__init__.py
litepolis_math/r_matrix_builder.py
litepolis_math/validation.py
litepolis_math/algorithms/__init__.py
litepolis_math/algorithms/kmeans.py
litepolis_math/algorithms/pca.py
litepolis_math-0.0.1.dist-info/METADATA
litepolis_math-0.0.1.dist-info/WHEEL
litepolis_math-0.0.1.dist-info/top_level.txt
litepolis_math-0.0.1.dist-info/RECORD
