Metadata-Version: 2.4
Name: litepolis-math
Version: 0.0.1
Summary: Mathematical algorithms module for LitePolis platform, providing PCA and KMeans implementations for user vote data analysis
Requires-Python: >=3.12
Requires-Dist: numpy
Requires-Dist: pandas
Requires-Dist: scikit-learn
